tsticker-0.1.22.dist-info/METADATA
tsticker-0.1.22.dist-info/WHEEL
tsticker-0.1.22.dist-info/entry_points.txt
tsticker-0.1.22.dist-info/licenses/LICENSE
tsticker/__init__.py
tsticker/cli.py
tsticker/const.py
tsticker/core/__init__.py
tsticker/core/const.py
tsticker/core/create.py
tsticker/utils.py
tsticker-0.1.22.dist-info/RECORD
